podmanapi/__init__.py
podmanapi/api.py
podmanapi/containers.py
podmanapi/exec.py
podmanapi/images.py
podmanapi/manifests.py
podmanapi/networks.py
podmanapi/system.py
podmanapi/volumes.py
podmanapi-0.3.dist-info/METADATA
podmanapi-0.3.dist-info/WHEEL
podmanapi-0.3.dist-info/top_level.txt
podmanapi-0.3.dist-info/RECORD
