Metadata-Version: 2.1
Name: podmanapi
Version: 0.3
Summary: Python package for Podman Rest API
Home-page: https://github.com/djotaku/podmanapis
Author: Eric Mesa
Author-email: UNKNOWN
License: GPLv3
Keywords: Podman,Docker,Containers
Platform: UNKNOWN
Requires-Dist: requests-unixsocket
